{
    "version": "0.10.0",
    "architecture": {
        "32bit": {
            "url": "https://github.com/sveltinio/sveltin/releases/download/v0.10.0/sveltin_0.10.0_Windows-i386.zip",
            "bin": [
                "sveltin.exe"
            ],
            "hash": "d9554563ebd3800e67d2fd3175a860810a04ebdd81f9f5e6b433c8981689ebaf"
        },
        "64bit": {
            "url": "https://github.com/sveltinio/sveltin/releases/download/v0.10.0/sveltin_0.10.0_Windows-x86_64.zip",
            "bin": [
                "sveltin.exe"
            ],
            "hash": "a32b15e248a581c97bec9077455331340ae824db7e2ab54cc389a998a38c39d5"
        }
    },
    "homepage": "https://sveltin.io",
    "license": "Apache-2.0",
    "description": "A powerful CLI for your next SvelteKit powered static website."
}